remarkable_sim/__init__.py
remarkable_sim/evsim.py
remarkable_sim/sim.py
remarkable_sim-1.0.6.dist-info/METADATA
remarkable_sim-1.0.6.dist-info/WHEEL
remarkable_sim-1.0.6.dist-info/entry_points.txt
remarkable_sim-1.0.6.dist-info/top_level.txt
remarkable_sim-1.0.6.dist-info/RECORD
