Metadata-Version: 2.1
Name: remarkable-sim
Version: 1.0.6
Summary: evdev/framebuffer simulation for reMarkable desktop development
Home-page: https://github.com/evidlo/remarkable_sim
Author: Evan Widloski
Author-email: evan@evanw.org
License: GPLv3
Keywords: remarkable evdev sim simulator simulation tablet
Platform: UNKNOWN
Classifier: Programming Language :: Python :: 3
